{
  "forum_url": "https://forum.xda-developers.com/redmi-note-5/development/rom-nitrogenos-t3972303", 
  "build_date": "20200215",
  "changelog": "====================\n     2020-02-15    \n====================\n\n * prebuilts/openssl\nb413f42  Revert \"Move linux libs to their version names\"  [PrateekPunetha]\n\n * vendor/nitrogen\nf78dacb  Add Vince to OTA  [PrateekPunetha]\n\n====================\n     2020-02-14    \n====================\n * OTA\n65bc55a  OTA: beryllium 13/02  [shahan-mik3]\n\n * build/make\n1bfb7a7  OTA: Fix prop  [Max]\n\n====================\n     2020-02-13    \n====================\n\n====================\n     2020-02-12    \n====================\n\n * vendor/nitrogen\nf75768a  Add X01BD to ota  [Jayant Deshmukh]\n\n====================\n     2020-02-11    \n====================\n\n====================\n     2020-02-10    \n====================\n * OTA\n906a62b  X01BD: add OTA details  [Jayant Deshmukh]\n\n====================\n     2020-02-09    \n====================\n\n",
  "url": "https://sourceforge.net/projects/nitrogen-project/files/vince/Nitrogen-OS-10-vince-20200215.zip/download", 
  "error": "false", 
  "filename": "Nitrogen-OS-10-vince-20200215.zip", 
  "filesize": "613324063",
  "md5": "d17d24662001666fc1856f687e44fde0",
  "addons": [
    {
      "url": "https://github.com/topjohnwu/Magisk/releases/download/v20.3/Magisk-v20.3.zip", 
      "summary": "Magisk", 
      "title": "Magisk"
    }, 
    {
      "url": "https://github.com/topjohnwu/Magisk/releases/download/v20.3/Magisk-uninstaller-20200110.zip", 
      "summary": "Magisk Uninstaller", 
      "title": "Magisk"
    }
  ], 
  "developer_url": "https://forum.xda-developers.com/member.php?u=9362058", 
  "website_url": "https://prateekpunetha.me/nos-10/", 
  "developer": "Prateek Punetha"
}
